postgrid/__init__.py
postgrid/_base_client.py
postgrid/_client.py
postgrid/_compat.py
postgrid/_constants.py
postgrid/_exceptions.py
postgrid/_files.py
postgrid/_models.py
postgrid/_qs.py
postgrid/_resource.py
postgrid/_response.py
postgrid/_streaming.py
postgrid/_types.py
postgrid/_version.py
postgrid/pagination.py
postgrid/py.typed
postgrid/_utils/__init__.py
postgrid/_utils/_compat.py
postgrid/_utils/_datetime_parse.py
postgrid/_utils/_logs.py
postgrid/_utils/_proxy.py
postgrid/_utils/_reflection.py
postgrid/_utils/_resources_proxy.py
postgrid/_utils/_streams.py
postgrid/_utils/_sync.py
postgrid/_utils/_transform.py
postgrid/_utils/_typing.py
postgrid/_utils/_utils.py
postgrid/lib/.keep
postgrid/resources/__init__.py
postgrid/resources/address_verification.py
postgrid/resources/intl_address_verification.py
postgrid/resources/print_mail/__init__.py
postgrid/resources/print_mail/bank_accounts.py
postgrid/resources/print_mail/campaigns.py
postgrid/resources/print_mail/cheques.py
postgrid/resources/print_mail/contacts.py
postgrid/resources/print_mail/letters.py
postgrid/resources/print_mail/mailing_list_imports.py
postgrid/resources/print_mail/mailing_lists.py
postgrid/resources/print_mail/postcards.py
postgrid/resources/print_mail/print_mail.py
postgrid/resources/print_mail/self_mailers.py
postgrid/resources/print_mail/sub_organizations.py
postgrid/resources/print_mail/templates.py
postgrid/resources/print_mail/order_profiles/__init__.py
postgrid/resources/print_mail/order_profiles/cheques.py
postgrid/resources/print_mail/order_profiles/letters.py
postgrid/resources/print_mail/order_profiles/order_profiles.py
postgrid/resources/print_mail/order_profiles/postcards.py
postgrid/resources/print_mail/order_profiles/self_mailers.py
postgrid/resources/print_mail/reports/__init__.py
postgrid/resources/print_mail/reports/exports.py
postgrid/resources/print_mail/reports/reports.py
postgrid/resources/print_mail/reports/samples.py
postgrid/types/__init__.py
postgrid_python-2.0.3.dist-info/METADATA
postgrid_python-2.0.3.dist-info/WHEEL
postgrid_python-2.0.3.dist-info/licenses/LICENSE
postgrid_python-2.0.3.dist-info/RECORD
